run_logger/__init__.py
run_logger/hasura_logger.py
run_logger/logger.py
run_logger/main.py
run_logger/params.py
run_logger/py.typed
run_logger-0.1.8.dist-info/LICENSE
run_logger-0.1.8.dist-info/WHEEL
run_logger-0.1.8.dist-info/METADATA
run_logger-0.1.8.dist-info/RECORD
