Metadata-Version: 2.1
Name: run-logger
Version: 0.1.8
Summary: A utility for logging runs.
Home-page: https://run-logger.readthedocs.io/en/latest/index.html
Author: Ethan Brooks
Author-email: ethanabrooks@gmail.com
Maintainer: Ethan Brooks
Maintainer-email: ethanabrooks@gmail.com
Requires-Python: >=3.8,<4.0
Classifier: Development Status :: 3 - Alpha
Classifier: Intended Audience :: Developers
Classifier: License :: OSI Approved :: MIT License
Classifier: Programming Language :: Python :: 3
Classifier: Programming Language :: Python :: 3.10
Classifier: Programming Language :: Python :: 3.11
Classifier: Programming Language :: Python :: 3.8
Classifier: Programming Language :: Python :: 3.9
Classifier: Programming Language :: Python :: Implementation :: PyPy
Classifier: Topic :: Software Development :: Libraries :: Python Modules
Classifier: Topic :: Utilities
Requires-Dist: PyYAML (>=6.0,<7.0)
Requires-Dist: gql (>=3.1.0,<4.0.0)
Requires-Dist: numpy (>=1.21.5,<2.0.0)
Project-URL: Repository, https://github.com/run-tracker/run-logger
